crabpack-1.1.1.dist-info/METADATA
crabpack-1.1.1.dist-info/WHEEL
crabpack-1.1.1.dist-info/licenses/LICENSE
crabpack/__init__.py
crabpack/crabpack.pyd
crabpack-1.1.1.dist-info/RECORD
